storage_text_field/__init__.py
storage_text_field/fields.py
storage_text_field/tests/__init__.py
storage_text_field/tests/models.py
storage_text_field/tests/settings.py
storage_text_field/tests/storages.py
storage_text_field/tests/tests.py
django_storage_text_field-1.5.2.dist-info/LICENSE
django_storage_text_field-1.5.2.dist-info/METADATA
django_storage_text_field-1.5.2.dist-info/WHEEL
django_storage_text_field-1.5.2.dist-info/top_level.txt
django_storage_text_field-1.5.2.dist-info/RECORD
